crypto_gltf/__init__.py
crypto_gltf/clib/Makefile
crypto_gltf/clib/bufferlib.c
crypto_gltf/clib/bufferlib.h
crypto_gltf/clib/clib.so
crypto_gltf/clib/clib_mac.so
crypto_gltf/clib/definitions.h
crypto_gltf/clib/main.c
crypto_gltf/clib/printlib.c
crypto_gltf/clib/printlib.h
crypto_gltf/clib/utils.c
crypto_gltf/clib/utils.h
crypto_gltf/data/__init__.py
crypto_gltf/data/asset_file_data_types.py
crypto_gltf/data/types.py
crypto_gltf/encrypt/__init__.py
crypto_gltf/encrypt/adaptive/__init__.py
crypto_gltf/encrypt/adaptive/base.py
crypto_gltf/encrypt/adaptive/cryptography/__init__.py
crypto_gltf/encrypt/adaptive/cryptography/aes_gcm.py
crypto_gltf/encrypt/adaptive/cryptography/key_gen.py
crypto_gltf/encrypt/adaptive/decrypt.py
crypto_gltf/encrypt/adaptive/encrypt.py
crypto_gltf/encrypt/adaptive/system.py
crypto_gltf/encrypt/adaptive/types.py
crypto_gltf/encrypt/adaptive/utils.py
crypto_gltf/encrypt/base.py
crypto_gltf/encrypt/deprecit/__init__.py
crypto_gltf/encrypt/deprecit/adaptive_v1/__init__.py
crypto_gltf/encrypt/deprecit/adaptive_v1/aes_gcm.py
crypto_gltf/encrypt/deprecit/adaptive_v1/base.py
crypto_gltf/encrypt/deprecit/adaptive_v1/decrypt.py
crypto_gltf/encrypt/deprecit/adaptive_v1/encrypt.py
crypto_gltf/encrypt/deprecit/adaptive_v1/system.py
crypto_gltf/encrypt/deprecit/adaptive_v1/types.py
crypto_gltf/encrypt/deprecit/adaptive_v1/utils.py
crypto_gltf/encrypt/deprecit/adaptive_v2/aes_gcm.py
crypto_gltf/encrypt/deprecit/adaptive_v2/base.py
crypto_gltf/encrypt/deprecit/adaptive_v2/decrypt.py
crypto_gltf/encrypt/deprecit/adaptive_v2/encrypt.py
crypto_gltf/encrypt/deprecit/adaptive_v2/key_gen.py
crypto_gltf/encrypt/deprecit/adaptive_v2/system.py
crypto_gltf/encrypt/deprecit/adaptive_v2/types.py
crypto_gltf/encrypt/deprecit/adaptive_v2/utils.py
crypto_gltf/encrypt/deprecit/ca/base.py
crypto_gltf/encrypt/deprecit/ca/ca.py
crypto_gltf/encrypt/deprecit/ca/decrypt.py
crypto_gltf/encrypt/deprecit/ca/encrypt.py
crypto_gltf/encrypt/deprecit/ca/params.py
crypto_gltf-0.1.14.dist-info/LICENCE
crypto_gltf-0.1.14.dist-info/METADATA
crypto_gltf-0.1.14.dist-info/WHEEL
crypto_gltf-0.1.14.dist-info/RECORD
